pdb_objects/__init__.py
pdb_objects-0.1.3.dist-info/LICENSE
pdb_objects-0.1.3.dist-info/METADATA
pdb_objects-0.1.3.dist-info/WHEEL
pdb_objects-0.1.3.dist-info/top_level.txt
pdb_objects-0.1.3.dist-info/RECORD
