Metadata-Version: 2.1
Name: pdb-objects
Version: 0.1.3
Summary: Object-oriented processing of Protein Databank (PDB) files
Home-page: https://github.com/georgewatson/pdb_objects
Author: George Watson
Author-email: george@georgewatson.me
License: MIT
Platform: UNKNOWN
Classifier: License :: OSI Approved :: MIT License
Classifier: Programming Language :: Python :: 3.5
Classifier: Topic :: Scientific/Engineering :: Bio-Informatics
